uniparser_moksha/__init__.py
uniparser_moksha/data_nodiacritics/__init__.py
uniparser_moksha/data_nodiacritics/bad_analyses.txt
uniparser_moksha/data_nodiacritics/lex_rules.txt
uniparser_moksha/data_nodiacritics/lexemes.txt
uniparser_moksha/data_nodiacritics/paradigms.txt
uniparser_moksha/data_strict/__init__.py
uniparser_moksha/data_strict/bad_analyses.txt
uniparser_moksha/data_strict/lex_rules.txt
uniparser_moksha/data_strict/lexemes.txt
uniparser_moksha/data_strict/paradigms.txt
uniparser_moksha-1.1.0.dist-info/LICENSE
uniparser_moksha-1.1.0.dist-info/METADATA
uniparser_moksha-1.1.0.dist-info/WHEEL
uniparser_moksha-1.1.0.dist-info/top_level.txt
uniparser_moksha-1.1.0.dist-info/RECORD
