Metadata-Version: 2.1
Name: uniparser-moksha
Version: 1.1.0
Summary: Rule-based morphological analysis for Moksha
Home-page: https://github.com/timarkh/uniparser-grammar-moksha
Author: Timofey Arkhangelskiy
Author-email: timarkh@gmail.com
License: UNKNOWN
Project-URL: Bug Tracker, https://github.com/timarkh/uniparser-grammar-moksha/issues
Platform: UNKNOWN
Classifier: Programming Language :: Python :: 3
Classifier: License :: OSI Approved :: MIT License
Classifier: Operating System :: OS Independent
Classifier: Intended Audience :: Science/Research
Classifier: Topic :: Text Processing :: Linguistic
Requires-Python: >=3.7
Requires-Dist: uniparser-morph (>=2.2.0)
Requires-Dist: importlib-resources
